LICENCE
MANIFEST.in
README.md
setup.py
rdfgenutils/__init__.py
rdfgenutils.egg-info/PKG-INFO
rdfgenutils.egg-info/SOURCES.txt
rdfgenutils.egg-info/dependency_links.txt
rdfgenutils.egg-info/top_level.txt