Metadata-Version: 1.0
Name: rdfgenutils
Version: 0.3.8
Summary: Some simple functions useful when generating RDF from non-RDF sources.
Home-page: https://github.com/iand/rdfgenutils
Author: Ian Davis
Author-email: nospam@iandavis.com
License: UNKNOWN
Platform: UNKNOWN
Classifier: Programming Language :: Python
Classifier: License :: Public Domain
Classifier: Operating System :: OS Independent
Classifier: Development Status :: 4 - Beta
Classifier: Intended Audience :: Developers
Classifier: Topic :: Software Development :: Libraries :: Python Modules
Classifier: Topic :: Database
